ml_express/__init__.py
ml_express/correlation.py
ml_express/custom_models.py
ml_express/data_cleaning.py
ml_express/data_processing.py
ml_express/dataframe.py
ml_express/eda.py
ml_express/feature_engineering.py
ml_express/imports.py
ml_express/model_explainer.py
ml_express/text_data_processing.py
ml_express/visualize.py
ml_express-0.1.3.dist-info/METADATA
ml_express-0.1.3.dist-info/WHEEL
ml_express-0.1.3.dist-info/entry_points.txt
ml_express-0.1.3.dist-info/top_level.txt
ml_express-0.1.3.dist-info/RECORD
