Metadata-Version: 2.1
Name: ml-express
Version: 0.1.3
Summary: A Python library for day to day data analysis and machine learning.
Home-page: https://github.com/ved93/ml-express
Author: Ved
Author-email: vpved93@gmail.com
License: License :: OSI Approved :: MIT License
Platform: UNKNOWN
Requires-Dist: scipy (>=1.2.1)
Requires-Dist: numpy (>=1.16.2)
Requires-Dist: pandas (>=0.24)
Requires-Dist: scikit-learn (>=0.23.2)
Requires-Dist: pandas-profiling (>=2.11.0)
Requires-Dist: matplotlib (>=3.0.0)
Requires-Dist: joblib (>=0.13.2)
Requires-Dist: Pillow (>=8.2.0)
Requires-Dist: seaborn (>=0.11.0)
Requires-Dist: graphviz (>=0.16)
Requires-Dist: sklearn-pandas (>=1.8.0)
Requires-Dist: pandas-summary (>=0.0.7)
